icetcore/__init__.py
icetcore/api.py
icetcore/change.md
icetcore/constant.py
icetcore/quote.py
icetcore/trade.py
icetcore/sample/__init__.py
icetcore/sample/sampple.py
icetcore/sample/strategy(OPTION).py
icetcore/sample/vannasampple.py
icetcore/sample/实时行情订阅.py
icetcore/sample/获取静态历史数据.py
icetcore-6.6.80.dist-info/LICENSE
icetcore-6.6.80.dist-info/METADATA
icetcore-6.6.80.dist-info/WHEEL
icetcore-6.6.80.dist-info/top_level.txt
icetcore-6.6.80.dist-info/RECORD
