Metadata-Version: 2.1
Name: icetcore
Version: 6.6.80
Summary: icetcore python api
Home-page: https://www.algostars.com.cn/
Author: zxlee
Author-email: zxlee@icetech.com.cn
Classifier: Environment :: Win32 (MS Windows)
Classifier: Programming Language :: Python :: 3.8
Classifier: Programming Language :: Python :: 3.9
Classifier: Programming Language :: Python :: 3.10
Classifier: Programming Language :: Python :: 3.11
Classifier: Programming Language :: Python :: 3.12
Classifier: Programming Language :: Python :: 3.13
Classifier: Operating System :: Microsoft :: Windows
Requires-Python: >=3.8.3
License-File: LICENSE
Requires-Dist: comtypes
Requires-Dist: pytz ==2023.3
